docs/__init__.py
docs/conf.py
docs/make_pdf.py
docs/api/__init__.py
docs/validation_report/generate_validation_figures.py
py_wake/__init__.py
py_wake/flow_map.py
py_wake/superposition_models.py
py_wake/version.py
py_wake/deficit_models/__init__.py
py_wake/deficit_models/deficit_model.py
py_wake/deficit_models/fuga.py
py_wake/deficit_models/gaussian.py
py_wake/deficit_models/gcl.py
py_wake/deficit_models/hybridinduction.py
py_wake/deficit_models/no_wake.py
py_wake/deficit_models/noj.py
py_wake/deficit_models/rankinehalfbody.py
py_wake/deficit_models/rans_lut.py
py_wake/deficit_models/rathmann.py
py_wake/deficit_models/selfsimilarity.py
py_wake/deficit_models/utils.py
py_wake/deficit_models/vortexcylinder.py
py_wake/deficit_models/vortexdipole.py
py_wake/deflection_models/__init__.py
py_wake/deflection_models/deflection_model.py
py_wake/deflection_models/fuga_deflection.py
py_wake/deflection_models/gcl_hill_vortex.py
py_wake/deflection_models/jimenez.py
py_wake/examples/__init__.py
py_wake/examples/compare_wake_models.py
py_wake/examples/hornsrev1_example.py
py_wake/examples/iea37_example.py
py_wake/examples/noj_terrain_following.py
py_wake/examples/data/NEG-Micon-2750.wtg
py_wake/examples/data/Vestas V112-3.0 MW.wtg
py_wake/examples/data/__init__.py
py_wake/examples/data/hornsrev1.py
py_wake/examples/data/lillgrund.py
py_wake/examples/data/time_series.npz
py_wake/examples/data/v52.py
py_wake/examples/data/ParqueFicticio/Ridge area   Sector 1   Height 200m   Flow inclination.grd
py_wake/examples/data/ParqueFicticio/Ridge area   Sector 1   Height 200m   Mean speed.grd
py_wake/examples/data/ParqueFicticio/Ridge area   Sector 1   Height 200m   Orographic speed.grd
py_wake/examples/data/ParqueFicticio/Ridge area   Sector 1   Height 200m   Orographic turn.grd
py_wake/examples/data/ParqueFicticio/Ridge area   Sector 1   Height 200m   Sector frequency.grd
py_wake/examples/data/ParqueFicticio/Ridge area   Sector 1   Height 200m   Turbulence intensity.grd
py_wake-2.6.14.dist-info/licenses/LICENSE
py_wake-2.6.14.dist-info/METADATA
py_wake-2.6.14.dist-info/WHEEL
py_wake-2.6.14.dist-info/top_level.txt
py_wake-2.6.14.dist-info/RECORD
