Metadata-Version: 2.4
Name: py_wake
Version: 2.6.14
Summary: Open source static wake modeling framework from DTU
Author: DTU Wind Energy
Author-email: "Mads M. Pedersen" <mmpe@dtu.dk>
License: MIT License
Project-URL: Documentation, https://topfarm.pages.windenergy.dtu.dk/PyWake/
Project-URL: Changelog, https://topfarm.pages.windenergy.dtu.dk/PyWake/notebooks/ChangeLog.html
Project-URL: Source code, https://gitlab.windenergy.dtu.dk/TOPFARM/PyWake
Project-URL: Issue tracker, https://gitlab.windenergy.dtu.dk/TOPFARM/PyWake/-/issues
Classifier: Programming Language :: Python :: 3
Classifier: Operating System :: OS Independent
Classifier: License :: OSI Approved :: MIT License
Requires-Python: >=3.7
License-File: LICENSE
Requires-Dist: git-lfs
Requires-Dist: matplotlib
Requires-Dist: numpy
Requires-Dist: xarray>=2024.6.1
Requires-Dist: netcdf4
Requires-Dist: h5netcdf
Requires-Dist: autograd
Requires-Dist: pyyaml
Requires-Dist: scipy
Requires-Dist: tqdm
Requires-Dist: joblib>=1.3
Requires-Dist: pooch
Provides-Extra: test
Requires-Dist: pytest; extra == "test"
Requires-Dist: pytest-cov; extra == "test"
Requires-Dist: psutil; extra == "test"
Requires-Dist: memory_profiler; extra == "test"
Requires-Dist: line_profiler; extra == "test"
Requires-Dist: scikit-learn; extra == "test"
Requires-Dist: surrogates-interface; extra == "test"
Requires-Dist: tensorflow; extra == "test"
Requires-Dist: ipywidgets; extra == "test"
Provides-Extra: docs
Requires-Dist: sphinx; extra == "docs"
Requires-Dist: sphinx_rtd_theme; extra == "docs"
Requires-Dist: ipywidgets; extra == "docs"
Requires-Dist: numpydoc; extra == "docs"
Requires-Dist: nbsphinx; extra == "docs"
Requires-Dist: sphinx_copybutton; extra == "docs"
Requires-Dist: sphinx_sitemap; extra == "docs"
Requires-Dist: ipympl; extra == "docs"
Requires-Dist: ipykernel; extra == "docs"
Requires-Dist: pypandoc; extra == "docs"
Requires-Dist: topfarm; extra == "docs"
Dynamic: license-file
